configures/__init__.py
configures/configuration.py
configures/exceptions.py
configures/logging.py
configures/secrets.py
configures/specification.py
configures/validator.py
configures/variable.py
configures/version.txt
configures-0.9.1.dist-info/licenses/LICENSE.md
configures-0.9.1.dist-info/METADATA
configures-0.9.1.dist-info/WHEEL
configures-0.9.1.dist-info/top_level.txt
configures-0.9.1.dist-info/zip-safe
configures-0.9.1.dist-info/RECORD
