Metadata-Version: 2.4
Name: configures
Version: 0.9.1
Summary: Streamlined application runtime configuration, validation and access
Author: Daniel Sissman
License-Expression: MIT
Project-URL: documentation, https://github.com/bluebinary/configures/blob/main/README.md
Project-URL: changelog, https://github.com/bluebinary/configures/blob/main/CHANGELOG.md
Project-URL: repository, https://github.com/bluebinary/configures
Project-URL: issues, https://github.com/bluebinary/configures/issues
Project-URL: homepage, https://github.com/bluebinary/configures
Keywords: configuration,secrets,environment variables,environment
Platform: any
Classifier: Programming Language :: Python :: 3
Classifier: Programming Language :: Python :: 3.10
Classifier: Programming Language :: Python :: 3.11
Classifier: Programming Language :: Python :: 3.12
Classifier: Programming Language :: Python :: 3.13
Requires-Python: >=3.10
License-File: LICENSE.md
Requires-Dist: pyyaml==6.0.*
Provides-Extra: development
Requires-Dist: black==24.10.*; extra == "development"
Requires-Dist: pytest==8.3.*; extra == "development"
Requires-Dist: pytest-codeblocks==0.17.*; extra == "development"
Requires-Dist: pyflakes; extra == "development"
Provides-Extra: distribution
Requires-Dist: build; extra == "distribution"
Requires-Dist: twine; extra == "distribution"
Requires-Dist: wheel; extra == "distribution"
Dynamic: license-file
